xkits_network/__init__.py
xkits_network/attr.py
xkits_network/book.py
xkits_network/inet.py
xkits_network-0.2.0.dist-info/LICENSE
xkits_network-0.2.0.dist-info/METADATA
xkits_network-0.2.0.dist-info/WHEEL
xkits_network-0.2.0.dist-info/top_level.txt
xkits_network-0.2.0.dist-info/zip-safe
xkits_network-0.2.0.dist-info/RECORD
