Metadata-Version: 2.1
Name: xkits-network
Version: 0.2.0
Summary: Network module
Home-page: https://github.com/bondbox/xnetwork/
Author: Mingzhe Zou
Author-email: zoumingzhe@outlook.com
License: MIT
Project-URL: Source Code, https://github.com/bondbox/xnetwork/
Project-URL: Bug Tracker, https://github.com/bondbox/xnetwork/issues
Project-URL: Documentation, https://github.com/bondbox/xnetwork/
Keywords: command-line,argparse,argcomplete
Platform: any
Classifier: Programming Language :: Python
Classifier: Programming Language :: Python :: 3
Requires-Python: >=3.8
License-File: LICENSE
Requires-Dist: xkits-command >=0.4.4
Requires-Dist: ping3
